<?xml version="1.0" encoding="UTF-8"?>
<tour apprev="20913" start="node1" appversion="7.1.2" hassounds="0">
  <panorama hideabout="1" id="node1">
    <input levelingpitch="0" width="1472" levelbias="0.400" levelingroll="0" leveltileurl="tiles/node1/cf_%c/l_%l/c_%x/tile_%y.jpg" levelbiashidpi="1.000" leveltilesize="510" height="1472" overlap="1">
      <level predecode="0" preload="0" height="1472" width="1472"/>
      <level predecode="0" preload="0" height="736" width="736"/>
      <level predecode="1" preload="1" height="368" width="368"/>
      <preview color="0x808080" strip="1"/>
    </input>
    <view fovmode="2" pannorth="0">
      <start fov="140.418" tilt="-6.30732" pan="-0.508452" projection="4"/>
      <flyin fov="170" tilt="-90" pan="0" projection="9"/>
      <min fovpixel="2" tilt="-90" pan="0"/>
      <max scaletofit="1" fovstereographic="330" fov="140" tilt="90" pan="360" fovfisheye="360"/>
    </view>
    <userdata title="세대현관" source="" info="" customnodeid="" comment="" altitude="121.87" heading="0" copyright="" nodeid="node1" author="" datetime="2024:12:18 07:58:43" longitude="126.677550" description="" latitude="36.649233" tags="2082203VR"/>
    <hotspots wordwrap="1" smoothmovement="0" height="20" width="180">
      <label wordwrap="1" borderalpha="1" textcolor="0x000000" textalpha="1" enabled="1" width="180" background="1" border="1" bordercolor="0x000000" backgroundcolor="0xffffff" height="20" borderradius="1" backgroundalpha="1"/>
      <polystyle handcursor="1" borderalpha="1" backgroundcolor="0x0000ff" mode="0" backgroundalpha="0.25098" bordercolor="0x0000ff"/>
      <hotspot url="{node19}" target="" title="현관" description="" skinid="ht_node" tilt="0.46" pan="-359.16" id="Point01"/>
    </hotspots>
    <media/>
    <transition type="crossdissolve" delay="none" softedge="0" blendtime="1" enabled="1" zoomafteroutfov="40" zoomspeed="2" zoomin="0" zoomafterinfov="140" zoomfov="40" zoomout="0" blendcolor="0x000000" zoomoutpause="1"/>
    <autorotate speed="0.020" delay="10.00" nodefilter="" enabled="1" returntohorizon="0.000" useanimation="0" horizonfromdefview="0" nodedelay="0.00" startloaded="0" noderandom="1"/>
    <animation syncanimationwithvideo="0" useinautorotation="0" animsequence="Animation01" clipsrandom="0"/>
    <control speedwheel="1" zoomcentercursor="1" sensitivity="8" lockedmouse="0" lockedkeyboardzoom="0" lockedkeyboard="0" invertcontrol="1" dblclickfullscreen="0" simulatemass="1" contextvr="1" contextprojections="0" invertwheel="0" contextfullscreen="1" rubberband="0" hideabout="1" lockedwheel="0"/>
  </panorama>
  <panorama hideabout="1" id="node19">
    <input levelingpitch="0" width="1472" levelbias="0.400" levelingroll="0" leveltileurl="tiles/node19/cf_%c/l_%l/c_%x/tile_%y.jpg" levelbiashidpi="1.000" leveltilesize="510" height="1472" overlap="1">
      <level predecode="0" preload="0" height="1472" width="1472"/>
      <level predecode="0" preload="0" height="736" width="736"/>
      <level predecode="1" preload="1" height="368" width="368"/>
      <preview color="0x808080" strip="1"/>
    </input>
    <view fovmode="2" pannorth="0">
      <start fov="129.808" tilt="-12.1069" pan="-178.575" projection="4"/>
      <flyin fov="170" tilt="-90" pan="0" projection="9"/>
      <min fovpixel="2" tilt="-90" pan="0"/>
      <max scaletofit="1" fovstereographic="330" fov="140" tilt="90" pan="360" fovfisheye="360"/>
    </view>
    <userdata title="현관" source="" info="" customnodeid="" comment="" altitude="121.87" heading="0" copyright="" nodeid="node19" author="" datetime="2024:12:18 07:58:41" longitude="126.677550" description="" latitude="36.649233" tags="2082203VR"/>
    <hotspots wordwrap="1" smoothmovement="0" height="20" width="180">
      <label wordwrap="1" borderalpha="1" textcolor="0x000000" textalpha="1" enabled="1" width="180" background="1" border="1" bordercolor="0x000000" backgroundcolor="0xffffff" height="20" borderradius="1" backgroundalpha="1"/>
      <polystyle handcursor="1" borderalpha="1" backgroundcolor="0x0000ff" mode="0" backgroundalpha="0.25098" bordercolor="0x0000ff"/>
      <hotspot url="{node1}" target="" title="세대현관" description="" skinid="ht_node" tilt="-14.49" pan="-335.12" id="Point01"/>
      <hotspot url="{node16}" target="" title="복도1" description="" skinid="ht_node" tilt="-30.31" pan="-182.08" id="Point02"/>
    </hotspots>
    <media/>
    <transition type="crossdissolve" delay="none" softedge="0" blendtime="1" enabled="1" zoomafteroutfov="40" zoomspeed="2" zoomin="0" zoomafterinfov="140" zoomfov="40" zoomout="0" blendcolor="0x000000" zoomoutpause="1"/>
    <autorotate speed="0.020" delay="10.00" nodefilter="" enabled="1" returntohorizon="0.000" useanimation="0" horizonfromdefview="0" nodedelay="0.00" startloaded="0" noderandom="1"/>
    <animation syncanimationwithvideo="0" useinautorotation="0" animsequence="Animation01" clipsrandom="0"/>
    <control speedwheel="1" zoomcentercursor="1" sensitivity="8" lockedmouse="0" lockedkeyboardzoom="0" lockedkeyboard="0" invertcontrol="1" dblclickfullscreen="0" simulatemass="1" contextvr="1" contextprojections="0" invertwheel="0" contextfullscreen="1" rubberband="0" hideabout="1" lockedwheel="0"/>
  </panorama>
  <panorama hideabout="1" id="node16">
    <input levelingpitch="0" width="1472" levelbias="0.400" levelingroll="0" leveltileurl="tiles/node16/cf_%c/l_%l/c_%x/tile_%y.jpg" levelbiashidpi="1.000" leveltilesize="510" height="1472" overlap="1">
      <level predecode="0" preload="0" height="1472" width="1472"/>
      <level predecode="0" preload="0" height="736" width="736"/>
      <level predecode="1" preload="1" height="368" width="368"/>
      <preview color="0x808080" strip="1"/>
    </input>
    <view fovmode="2" pannorth="0">
      <start fov="140.418" tilt="-16.6769" pan="175.575" projection="4"/>
      <flyin fov="170" tilt="-90" pan="0" projection="9"/>
      <min fovpixel="2" tilt="-90" pan="0"/>
      <max scaletofit="1" fovstereographic="330" fov="140" tilt="90" pan="360" fovfisheye="360"/>
    </view>
    <userdata title="복도1" source="" info="" customnodeid="" comment="" altitude="121.87" heading="0" copyright="" nodeid="node16" author="" datetime="2024:12:18 07:58:33" longitude="126.677550" description="" latitude="36.649233" tags="2082203VR"/>
    <hotspots wordwrap="1" smoothmovement="0" height="20" width="180">
      <label wordwrap="1" borderalpha="1" textcolor="0x000000" textalpha="1" enabled="1" width="180" background="1" border="1" bordercolor="0x000000" backgroundcolor="0xffffff" height="20" borderradius="1" backgroundalpha="1"/>
      <polystyle handcursor="1" borderalpha="1" backgroundcolor="0x0000ff" mode="0" backgroundalpha="0.25098" bordercolor="0x0000ff"/>
      <hotspot url="{node14}" target="" title="팬트리" description="" skinid="ht_node" tilt="-39.08" pan="-158.91" id="Point01"/>
      <hotspot url="{node15}" target="" title="침실3" description="" skinid="ht_node" tilt="-36.76" pan="-216.66" id="Point02"/>
      <hotspot url="{node12}" target="" title="복도2" description="" skinid="ht_node" tilt="-20.43" pan="-183.76" id="Point03"/>
      <hotspot url="{node19}" target="" title="현관" description="" skinid="ht_node" tilt="-38.42" pan="-71.19" id="Point04"/>
      <hotspot url="{node18}" target="" title="욕실1" description="" skinid="ht_node" tilt="-22.99" pan="-355.9" id="Point05"/>
      <hotspot url="{node17}" target="" title="침실4" description="" skinid="ht_node" tilt="-29.1" pan="-334.12" id="Point06"/>
    </hotspots>
    <media/>
    <transition type="crossdissolve" delay="none" softedge="0" blendtime="1" enabled="1" zoomafteroutfov="40" zoomspeed="2" zoomin="0" zoomafterinfov="140" zoomfov="40" zoomout="0" blendcolor="0x000000" zoomoutpause="1"/>
    <autorotate speed="0.020" delay="10.00" nodefilter="" enabled="1" returntohorizon="0.000" useanimation="0" horizonfromdefview="0" nodedelay="0.00" startloaded="0" noderandom="1"/>
    <animation syncanimationwithvideo="0" useinautorotation="0" animsequence="Animation01" clipsrandom="0"/>
    <control speedwheel="1" zoomcentercursor="1" sensitivity="8" lockedmouse="0" lockedkeyboardzoom="0" lockedkeyboard="0" invertcontrol="1" dblclickfullscreen="0" simulatemass="1" contextvr="1" contextprojections="0" invertwheel="0" contextfullscreen="1" rubberband="0" hideabout="1" lockedwheel="0"/>
  </panorama>
  <panorama hideabout="1" id="node18">
    <input levelingpitch="0" width="1472" levelbias="0.400" levelingroll="0" leveltileurl="tiles/node18/cf_%c/l_%l/c_%x/tile_%y.jpg" levelbiashidpi="1.000" leveltilesize="510" height="1472" overlap="1">
      <level predecode="0" preload="0" height="1472" width="1472"/>
      <level predecode="0" preload="0" height="736" width="736"/>
      <level predecode="1" preload="1" height="368" width="368"/>
      <preview color="0x808080" strip="1"/>
    </input>
    <view fovmode="2" pannorth="0">
      <start fov="140.418" tilt="-30.818" pan="-58.8035" projection="4"/>
      <flyin fov="170" tilt="-90" pan="0" projection="9"/>
      <min fovpixel="2" tilt="-90" pan="0"/>
      <max scaletofit="1" fovstereographic="330" fov="140" tilt="90" pan="360" fovfisheye="360"/>
    </view>
    <userdata title="욕실1" source="" info="" customnodeid="" comment="" altitude="121.87" heading="0" copyright="" nodeid="node18" author="" datetime="2024:12:18 07:58:38" longitude="126.677550" description="" latitude="36.649233" tags="2082203VR"/>
    <hotspots wordwrap="1" smoothmovement="0" height="20" width="180">
      <label wordwrap="1" borderalpha="1" textcolor="0x000000" textalpha="1" enabled="1" width="180" background="1" border="1" bordercolor="0x000000" backgroundcolor="0xffffff" height="20" borderradius="1" backgroundalpha="1"/>
      <polystyle handcursor="1" borderalpha="1" backgroundcolor="0x0000ff" mode="0" backgroundalpha="0.25098" bordercolor="0x0000ff"/>
      <hotspot url="{node16}" target="" title="복도1" description="" skinid="ht_node" tilt="-44.6" pan="-222.52" id="Point01"/>
    </hotspots>
    <media/>
    <transition type="crossdissolve" delay="none" softedge="0" blendtime="1" enabled="1" zoomafteroutfov="40" zoomspeed="2" zoomin="0" zoomafterinfov="140" zoomfov="40" zoomout="0" blendcolor="0x000000" zoomoutpause="1"/>
    <autorotate speed="0.020" delay="10.00" nodefilter="" enabled="1" returntohorizon="0.000" useanimation="0" horizonfromdefview="0" nodedelay="0.00" startloaded="0" noderandom="1"/>
    <animation syncanimationwithvideo="0" useinautorotation="0" animsequence="Animation01" clipsrandom="0"/>
    <control speedwheel="1" zoomcentercursor="1" sensitivity="8" lockedmouse="0" lockedkeyboardzoom="0" lockedkeyboard="0" invertcontrol="1" dblclickfullscreen="0" simulatemass="1" contextvr="1" contextprojections="0" invertwheel="0" contextfullscreen="1" rubberband="0" hideabout="1" lockedwheel="0"/>
  </panorama>
  <panorama hideabout="1" id="node17">
    <input levelingpitch="0" width="1472" levelbias="0.400" levelingroll="0" leveltileurl="tiles/node17/cf_%c/l_%l/c_%x/tile_%y.jpg" levelbiashidpi="1.000" leveltilesize="510" height="1472" overlap="1">
      <level predecode="0" preload="0" height="1472" width="1472"/>
      <level predecode="0" preload="0" height="736" width="736"/>
      <level predecode="1" preload="1" height="368" width="368"/>
      <preview color="0x808080" strip="1"/>
    </input>
    <view fovmode="2" pannorth="0">
      <start fov="140.418" tilt="-17.6126" pan="-179.911" projection="4"/>
      <flyin fov="170" tilt="-90" pan="0" projection="9"/>
      <min fovpixel="2" tilt="-90" pan="0"/>
      <max scaletofit="1" fovstereographic="330" fov="140" tilt="90" pan="360" fovfisheye="360"/>
    </view>
    <userdata title="침실4" source="" info="" customnodeid="" comment="" altitude="121.87" heading="0" copyright="" nodeid="node17" author="" datetime="2024:12:18 07:58:35" longitude="126.677550" description="" latitude="36.649233" tags="2082203VR"/>
    <hotspots wordwrap="1" smoothmovement="0" height="20" width="180">
      <label wordwrap="1" borderalpha="1" textcolor="0x000000" textalpha="1" enabled="1" width="180" background="1" border="1" bordercolor="0x000000" backgroundcolor="0xffffff" height="20" borderradius="1" backgroundalpha="1"/>
      <polystyle handcursor="1" borderalpha="1" backgroundcolor="0x0000ff" mode="0" backgroundalpha="0.25098" bordercolor="0x0000ff"/>
      <hotspot url="{node16}" target="" title="복도1" description="" skinid="ht_node" tilt="-25.8" pan="-212.39" id="Point01"/>
    </hotspots>
    <media/>
    <transition type="crossdissolve" delay="none" softedge="0" blendtime="1" enabled="1" zoomafteroutfov="40" zoomspeed="2" zoomin="0" zoomafterinfov="140" zoomfov="40" zoomout="0" blendcolor="0x000000" zoomoutpause="1"/>
    <autorotate speed="0.020" delay="10.00" nodefilter="" enabled="1" returntohorizon="0.000" useanimation="0" horizonfromdefview="0" nodedelay="0.00" startloaded="0" noderandom="1"/>
    <animation syncanimationwithvideo="0" useinautorotation="0" animsequence="Animation01" clipsrandom="0"/>
    <control speedwheel="1" zoomcentercursor="1" sensitivity="8" lockedmouse="0" lockedkeyboardzoom="0" lockedkeyboard="0" invertcontrol="1" dblclickfullscreen="0" simulatemass="1" contextvr="1" contextprojections="0" invertwheel="0" contextfullscreen="1" rubberband="0" hideabout="1" lockedwheel="0"/>
  </panorama>
  <panorama hideabout="1" id="node15">
    <input levelingpitch="0" width="1472" levelbias="0.400" levelingroll="0" leveltileurl="tiles/node15/cf_%c/l_%l/c_%x/tile_%y.jpg" levelbiashidpi="1.000" leveltilesize="510" height="1472" overlap="1">
      <level predecode="0" preload="0" height="1472" width="1472"/>
      <level predecode="0" preload="0" height="736" width="736"/>
      <level predecode="1" preload="1" height="368" width="368"/>
      <preview color="0x808080" strip="1"/>
    </input>
    <view fovmode="2" pannorth="0">
      <start fov="140.418" tilt="-16.9682" pan="178.575" projection="4"/>
      <flyin fov="170" tilt="-90" pan="0" projection="9"/>
      <min fovpixel="2" tilt="-90" pan="0"/>
      <max scaletofit="1" fovstereographic="330" fov="140" tilt="90" pan="360" fovfisheye="360"/>
    </view>
    <userdata title="침실3" source="" info="" customnodeid="" comment="" altitude="121.87" heading="0" copyright="" nodeid="node15" author="" datetime="2024:12:18 07:58:30" longitude="126.677550" description="" latitude="36.649233" tags="2082203VR"/>
    <hotspots wordwrap="1" smoothmovement="0" height="20" width="180">
      <label wordwrap="1" borderalpha="1" textcolor="0x000000" textalpha="1" enabled="1" width="180" background="1" border="1" bordercolor="0x000000" backgroundcolor="0xffffff" height="20" borderradius="1" backgroundalpha="1"/>
      <polystyle handcursor="1" borderalpha="1" backgroundcolor="0x0000ff" mode="0" backgroundalpha="0.25098" bordercolor="0x0000ff"/>
      <hotspot url="{node16}" target="" title="복도1" description="" skinid="ht_node" tilt="-28.14" pan="-210.87" id="Point01"/>
    </hotspots>
    <media/>
    <transition type="crossdissolve" delay="none" softedge="0" blendtime="1" enabled="1" zoomafteroutfov="40" zoomspeed="2" zoomin="0" zoomafterinfov="140" zoomfov="40" zoomout="0" blendcolor="0x000000" zoomoutpause="1"/>
    <autorotate speed="0.020" delay="10.00" nodefilter="" enabled="1" returntohorizon="0.000" useanimation="0" horizonfromdefview="0" nodedelay="0.00" startloaded="0" noderandom="1"/>
    <animation syncanimationwithvideo="0" useinautorotation="0" animsequence="Animation01" clipsrandom="0"/>
    <control speedwheel="1" zoomcentercursor="1" sensitivity="8" lockedmouse="0" lockedkeyboardzoom="0" lockedkeyboard="0" invertcontrol="1" dblclickfullscreen="0" simulatemass="1" contextvr="1" contextprojections="0" invertwheel="0" contextfullscreen="1" rubberband="0" hideabout="1" lockedwheel="0"/>
  </panorama>
  <panorama hideabout="1" id="node14">
    <input levelingpitch="0" width="1472" levelbias="0.400" levelingroll="0" leveltileurl="tiles/node14/cf_%c/l_%l/c_%x/tile_%y.jpg" levelbiashidpi="1.000" leveltilesize="510" height="1472" overlap="1">
      <level predecode="0" preload="0" height="1472" width="1472"/>
      <level predecode="0" preload="0" height="736" width="736"/>
      <level predecode="1" preload="1" height="368" width="368"/>
      <preview color="0x808080" strip="1"/>
    </input>
    <view fovmode="2" pannorth="0">
      <start fov="140.418" tilt="-15.4096" pan="-177.455" projection="4"/>
      <flyin fov="170" tilt="-90" pan="0" projection="9"/>
      <min fovpixel="2" tilt="-90" pan="0"/>
      <max scaletofit="1" fovstereographic="330" fov="140" tilt="90" pan="360" fovfisheye="360"/>
    </view>
    <userdata title="팬트리" source="" info="" customnodeid="" comment="" altitude="121.87" heading="0" copyright="" nodeid="node14" author="" datetime="2024:12:18 07:58:28" longitude="126.677550" description="" latitude="36.649233" tags="2082203VR"/>
    <hotspots wordwrap="1" smoothmovement="0" height="20" width="180">
      <label wordwrap="1" borderalpha="1" textcolor="0x000000" textalpha="1" enabled="1" width="180" background="1" border="1" bordercolor="0x000000" backgroundcolor="0xffffff" height="20" borderradius="1" backgroundalpha="1"/>
      <polystyle handcursor="1" borderalpha="1" backgroundcolor="0x0000ff" mode="0" backgroundalpha="0.25098" bordercolor="0x0000ff"/>
      <hotspot url="{node16}" target="" title="복도1" description="" skinid="ht_node" tilt="-40.91" pan="-181.51" id="Point01"/>
    </hotspots>
    <media/>
    <transition type="crossdissolve" delay="none" softedge="0" blendtime="1" enabled="1" zoomafteroutfov="40" zoomspeed="2" zoomin="0" zoomafterinfov="140" zoomfov="40" zoomout="0" blendcolor="0x000000" zoomoutpause="1"/>
    <autorotate speed="0.020" delay="10.00" nodefilter="" enabled="1" returntohorizon="0.000" useanimation="0" horizonfromdefview="0" nodedelay="0.00" startloaded="0" noderandom="1"/>
    <animation syncanimationwithvideo="0" useinautorotation="0" animsequence="Animation01" clipsrandom="0"/>
    <control speedwheel="1" zoomcentercursor="1" sensitivity="8" lockedmouse="0" lockedkeyboardzoom="0" lockedkeyboard="0" invertcontrol="1" dblclickfullscreen="0" simulatemass="1" contextvr="1" contextprojections="0" invertwheel="0" contextfullscreen="1" rubberband="0" hideabout="1" lockedwheel="0"/>
  </panorama>
  <panorama hideabout="1" id="node12">
    <input levelingpitch="0" width="1472" levelbias="0.400" levelingroll="0" leveltileurl="tiles/node12/cf_%c/l_%l/c_%x/tile_%y.jpg" levelbiashidpi="1.000" leveltilesize="510" height="1472" overlap="1">
      <level predecode="0" preload="0" height="1472" width="1472"/>
      <level predecode="0" preload="0" height="736" width="736"/>
      <level predecode="1" preload="1" height="368" width="368"/>
      <preview color="0x808080" strip="1"/>
    </input>
    <view fovmode="2" pannorth="0">
      <start fov="137.201" tilt="-12.4283" pan="139.274" projection="4"/>
      <flyin fov="170" tilt="-90" pan="0" projection="9"/>
      <min fovpixel="2" tilt="-90" pan="0"/>
      <max scaletofit="1" fovstereographic="330" fov="140" tilt="90" pan="360" fovfisheye="360"/>
    </view>
    <userdata title="복도2" source="" info="" customnodeid="" comment="" altitude="121.87" heading="0" copyright="" nodeid="node12" author="" datetime="2024:12:18 07:58:22" longitude="126.677550" description="" latitude="36.649233" tags="2082203VR"/>
    <hotspots wordwrap="1" smoothmovement="0" height="20" width="180">
      <label wordwrap="1" borderalpha="1" textcolor="0x000000" textalpha="1" enabled="1" width="180" background="1" border="1" bordercolor="0x000000" backgroundcolor="0xffffff" height="20" borderradius="1" backgroundalpha="1"/>
      <polystyle handcursor="1" borderalpha="1" backgroundcolor="0x0000ff" mode="0" backgroundalpha="0.25098" bordercolor="0x0000ff"/>
      <hotspot url="{node13}" target="" title="거실" description="" skinid="ht_node" tilt="-29.34" pan="-187.18" id="Point01"/>
      <hotspot url="{node16}" target="" title="복도1" description="" skinid="ht_node" tilt="-21.38" pan="-240.53" id="Point02"/>
      <hotspot url="{node11}" target="" title="침실2" description="" skinid="ht_node" tilt="-20.64" pan="-129.39" id="Point03"/>
      <hotspot url="{node3}" target="" title="주방" description="" skinid="ht_node" tilt="-30.95" pan="-316.22" id="Point04"/>
    </hotspots>
    <media/>
    <transition type="crossdissolve" delay="none" softedge="0" blendtime="1" enabled="1" zoomafteroutfov="40" zoomspeed="2" zoomin="0" zoomafterinfov="140" zoomfov="40" zoomout="0" blendcolor="0x000000" zoomoutpause="1"/>
    <autorotate speed="0.020" delay="10.00" nodefilter="" enabled="1" returntohorizon="0.000" useanimation="0" horizonfromdefview="0" nodedelay="0.00" startloaded="0" noderandom="1"/>
    <animation syncanimationwithvideo="0" useinautorotation="0" animsequence="Animation01" clipsrandom="0"/>
    <control speedwheel="1" zoomcentercursor="1" sensitivity="8" lockedmouse="0" lockedkeyboardzoom="0" lockedkeyboard="0" invertcontrol="1" dblclickfullscreen="0" simulatemass="1" contextvr="1" contextprojections="0" invertwheel="0" contextfullscreen="1" rubberband="0" hideabout="1" lockedwheel="0"/>
  </panorama>
  <panorama hideabout="1" id="node13">
    <input levelingpitch="0" width="1472" levelbias="0.400" levelingroll="0" leveltileurl="tiles/node13/cf_%c/l_%l/c_%x/tile_%y.jpg" levelbiashidpi="1.000" leveltilesize="510" height="1472" overlap="1">
      <level predecode="0" preload="0" height="1472" width="1472"/>
      <level predecode="0" preload="0" height="736" width="736"/>
      <level predecode="1" preload="1" height="368" width="368"/>
      <preview color="0x808080" strip="1"/>
    </input>
    <view fovmode="2" pannorth="0">
      <start fov="148.415" tilt="-3.47891" pan="92.9586" projection="4"/>
      <flyin fov="170" tilt="-90" pan="0" projection="9"/>
      <min fovpixel="2" tilt="-90" pan="0"/>
      <max scaletofit="1" fovstereographic="330" fov="140" tilt="90" pan="360" fovfisheye="360"/>
    </view>
    <userdata title="거실" source="" info="" customnodeid="" comment="" altitude="121.87" heading="0" copyright="" nodeid="node13" author="" datetime="2024:12:18 07:58:25" longitude="126.677550" description="" latitude="36.649233" tags="2082203VR"/>
    <hotspots wordwrap="1" smoothmovement="0" height="20" width="180">
      <label wordwrap="1" borderalpha="1" textcolor="0x000000" textalpha="1" enabled="1" width="180" background="1" border="1" bordercolor="0x000000" backgroundcolor="0xffffff" height="20" borderradius="1" backgroundalpha="1"/>
      <polystyle handcursor="1" borderalpha="1" backgroundcolor="0x0000ff" mode="0" backgroundalpha="0.25098" bordercolor="0x0000ff"/>
      <hotspot url="{node12}" target="" title="복도2" description="" skinid="ht_node" tilt="-20.67" pan="-186.64" id="Point01"/>
      <hotspot url="{node16}" target="" title="복도1" description="" skinid="ht_node" tilt="-21.53" pan="-138.42" id="Point02"/>
      <hotspot url="{node10}" target="" title="침실1" description="" skinid="ht_node" tilt="-16.15" pan="-229.94" id="Point03"/>
    </hotspots>
    <media/>
    <transition type="crossdissolve" delay="none" softedge="0" blendtime="1" enabled="1" zoomafteroutfov="40" zoomspeed="2" zoomin="0" zoomafterinfov="140" zoomfov="40" zoomout="0" blendcolor="0x000000" zoomoutpause="1"/>
    <autorotate speed="0.020" delay="10.00" nodefilter="" enabled="1" returntohorizon="0.000" useanimation="0" horizonfromdefview="0" nodedelay="0.00" startloaded="0" noderandom="1"/>
    <animation syncanimationwithvideo="0" useinautorotation="0" animsequence="Animation01" clipsrandom="0"/>
    <control speedwheel="1" zoomcentercursor="1" sensitivity="8" lockedmouse="0" lockedkeyboardzoom="0" lockedkeyboard="0" invertcontrol="1" dblclickfullscreen="0" simulatemass="1" contextvr="1" contextprojections="0" invertwheel="0" contextfullscreen="1" rubberband="0" hideabout="1" lockedwheel="0"/>
  </panorama>
  <panorama hideabout="1" id="node3">
    <input levelingpitch="0" width="1472" levelbias="0.400" levelingroll="0" leveltileurl="tiles/node3/cf_%c/l_%l/c_%x/tile_%y.jpg" levelbiashidpi="1.000" leveltilesize="510" height="1472" overlap="1">
      <level predecode="0" preload="0" height="1472" width="1472"/>
      <level predecode="0" preload="0" height="736" width="736"/>
      <level predecode="1" preload="1" height="368" width="368"/>
      <preview color="0x808080" strip="1"/>
    </input>
    <view fovmode="2" pannorth="0">
      <start fov="148.415" tilt="-14.1398" pan="95.5545" projection="4"/>
      <flyin fov="170" tilt="-90" pan="0" projection="9"/>
      <min fovpixel="2" tilt="-90" pan="0"/>
      <max scaletofit="1" fovstereographic="330" fov="140" tilt="90" pan="360" fovfisheye="360"/>
    </view>
    <userdata title="주방" source="" info="" customnodeid="" comment="" altitude="121.87" heading="0" copyright="" nodeid="node3" author="" datetime="2024:12:18 07:57:59" longitude="126.677550" description="" latitude="36.649233" tags="2082203VR"/>
    <hotspots wordwrap="1" smoothmovement="0" height="20" width="180">
      <label wordwrap="1" borderalpha="1" textcolor="0x000000" textalpha="1" enabled="1" width="180" background="1" border="1" bordercolor="0x000000" backgroundcolor="0xffffff" height="20" borderradius="1" backgroundalpha="1"/>
      <polystyle handcursor="1" borderalpha="1" backgroundcolor="0x0000ff" mode="0" backgroundalpha="0.25098" bordercolor="0x0000ff"/>
      <hotspot url="{node2}" target="" title="다용도실" description="" skinid="ht_node" tilt="-22.63" pan="-268.99" id="Point01"/>
      <hotspot url="{node12}" target="" title="복도2" description="" skinid="ht_node" tilt="-35.79" pan="-241.62" id="Point02"/>
      <hotspot url="{node4}" target="" title="복도3" description="" skinid="ht_node" tilt="-22.79" pan="-85.83" id="Point03"/>
    </hotspots>
    <media/>
    <transition type="crossdissolve" delay="none" softedge="0" blendtime="1" enabled="1" zoomafteroutfov="40" zoomspeed="2" zoomin="0" zoomafterinfov="140" zoomfov="40" zoomout="0" blendcolor="0x000000" zoomoutpause="1"/>
    <autorotate speed="0.020" delay="10.00" nodefilter="" enabled="1" returntohorizon="0.000" useanimation="0" horizonfromdefview="0" nodedelay="0.00" startloaded="0" noderandom="1"/>
    <animation syncanimationwithvideo="0" useinautorotation="0" animsequence="Animation01" clipsrandom="0"/>
    <control speedwheel="1" zoomcentercursor="1" sensitivity="8" lockedmouse="0" lockedkeyboardzoom="0" lockedkeyboard="0" invertcontrol="1" dblclickfullscreen="0" simulatemass="1" contextvr="1" contextprojections="0" invertwheel="0" contextfullscreen="1" rubberband="0" hideabout="1" lockedwheel="0"/>
  </panorama>
  <panorama hideabout="1" id="node2">
    <input levelingpitch="0" width="1472" levelbias="0.400" levelingroll="0" leveltileurl="tiles/node2/cf_%c/l_%l/c_%x/tile_%y.jpg" levelbiashidpi="1.000" leveltilesize="510" height="1472" overlap="1">
      <level predecode="0" preload="0" height="1472" width="1472"/>
      <level predecode="0" preload="0" height="736" width="736"/>
      <level predecode="1" preload="1" height="368" width="368"/>
      <preview color="0x808080" strip="1"/>
    </input>
    <view fovmode="2" pannorth="0">
      <start fov="148.415" tilt="-16.737" pan="-90.9394" projection="4"/>
      <flyin fov="170" tilt="-90" pan="0" projection="9"/>
      <min fovpixel="2" tilt="-90" pan="0"/>
      <max scaletofit="1" fovstereographic="330" fov="140" tilt="90" pan="360" fovfisheye="360"/>
    </view>
    <userdata title="다용도실" source="" info="" customnodeid="" comment="" altitude="121.87" heading="0" copyright="" nodeid="node2" author="" datetime="2024:12:18 07:57:56" longitude="126.677550" description="" latitude="36.649233" tags="2082203VR"/>
    <hotspots wordwrap="1" smoothmovement="0" height="20" width="180">
      <label wordwrap="1" borderalpha="1" textcolor="0x000000" textalpha="1" enabled="1" width="180" background="1" border="1" bordercolor="0x000000" backgroundcolor="0xffffff" height="20" borderradius="1" backgroundalpha="1"/>
      <polystyle handcursor="1" borderalpha="1" backgroundcolor="0x0000ff" mode="0" backgroundalpha="0.25098" bordercolor="0x0000ff"/>
      <hotspot url="{node3}" target="" title="주방" description="" skinid="ht_node" tilt="-34.47" pan="-97.88" id="Point01"/>
    </hotspots>
    <media/>
    <transition type="crossdissolve" delay="none" softedge="0" blendtime="1" enabled="1" zoomafteroutfov="40" zoomspeed="2" zoomin="0" zoomafterinfov="140" zoomfov="40" zoomout="0" blendcolor="0x000000" zoomoutpause="1"/>
    <autorotate speed="0.020" delay="10.00" nodefilter="" enabled="1" returntohorizon="0.000" useanimation="0" horizonfromdefview="0" nodedelay="0.00" startloaded="0" noderandom="1"/>
    <animation syncanimationwithvideo="0" useinautorotation="0" animsequence="Animation01" clipsrandom="0"/>
    <control speedwheel="1" zoomcentercursor="1" sensitivity="8" lockedmouse="0" lockedkeyboardzoom="0" lockedkeyboard="0" invertcontrol="1" dblclickfullscreen="0" simulatemass="1" contextvr="1" contextprojections="0" invertwheel="0" contextfullscreen="1" rubberband="0" hideabout="1" lockedwheel="0"/>
  </panorama>
  <panorama hideabout="1" id="node11">
    <input levelingpitch="0" width="1472" levelbias="0.400" levelingroll="0" leveltileurl="tiles/node11/cf_%c/l_%l/c_%x/tile_%y.jpg" levelbiashidpi="1.000" leveltilesize="510" height="1472" overlap="1">
      <level predecode="0" preload="0" height="1472" width="1472"/>
      <level predecode="0" preload="0" height="736" width="736"/>
      <level predecode="1" preload="1" height="368" width="368"/>
      <preview color="0x808080" strip="1"/>
    </input>
    <view fovmode="2" pannorth="0">
      <start fov="148.415" tilt="-18.4889" pan="-171.754" projection="4"/>
      <flyin fov="170" tilt="-90" pan="0" projection="9"/>
      <min fovpixel="2" tilt="-90" pan="0"/>
      <max scaletofit="1" fovstereographic="330" fov="140" tilt="90" pan="360" fovfisheye="360"/>
    </view>
    <userdata title="침실2" source="" info="" customnodeid="" comment="" altitude="121.87" heading="0" copyright="" nodeid="node11" author="" datetime="2024:12:18 07:58:20" longitude="126.677550" description="" latitude="36.649233" tags="2082203VR"/>
    <hotspots wordwrap="1" smoothmovement="0" height="20" width="180">
      <label wordwrap="1" borderalpha="1" textcolor="0x000000" textalpha="1" enabled="1" width="180" background="1" border="1" bordercolor="0x000000" backgroundcolor="0xffffff" height="20" borderradius="1" backgroundalpha="1"/>
      <polystyle handcursor="1" borderalpha="1" backgroundcolor="0x0000ff" mode="0" backgroundalpha="0.25098" bordercolor="0x0000ff"/>
      <hotspot url="{node12}" target="" title="복도2" description="" skinid="ht_node" tilt="-29.39" pan="-157.68" id="Point01"/>
    </hotspots>
    <media/>
    <transition type="crossdissolve" delay="none" softedge="0" blendtime="1" enabled="1" zoomafteroutfov="40" zoomspeed="2" zoomin="0" zoomafterinfov="140" zoomfov="40" zoomout="0" blendcolor="0x000000" zoomoutpause="1"/>
    <autorotate speed="0.020" delay="10.00" nodefilter="" enabled="1" returntohorizon="0.000" useanimation="0" horizonfromdefview="0" nodedelay="0.00" startloaded="0" noderandom="1"/>
    <animation syncanimationwithvideo="0" useinautorotation="0" animsequence="Animation01" clipsrandom="0"/>
    <control speedwheel="1" zoomcentercursor="1" sensitivity="8" lockedmouse="0" lockedkeyboardzoom="0" lockedkeyboard="0" invertcontrol="1" dblclickfullscreen="0" simulatemass="1" contextvr="1" contextprojections="0" invertwheel="0" contextfullscreen="1" rubberband="0" hideabout="1" lockedwheel="0"/>
  </panorama>
  <panorama hideabout="1" id="node10">
    <input levelingpitch="0" width="1472" levelbias="0.400" levelingroll="0" leveltileurl="tiles/node10/cf_%c/l_%l/c_%x/tile_%y.jpg" levelbiashidpi="1.000" leveltilesize="510" height="1472" overlap="1">
      <level predecode="0" preload="0" height="1472" width="1472"/>
      <level predecode="0" preload="0" height="736" width="736"/>
      <level predecode="1" preload="1" height="368" width="368"/>
      <preview color="0x808080" strip="1"/>
    </input>
    <view fovmode="2" pannorth="0">
      <start fov="148.415" tilt="-15.3086" pan="-92.9941" projection="4"/>
      <flyin fov="170" tilt="-90" pan="0" projection="9"/>
      <min fovpixel="2" tilt="-90" pan="0"/>
      <max scaletofit="1" fovstereographic="330" fov="140" tilt="90" pan="360" fovfisheye="360"/>
    </view>
    <userdata title="침실1" source="" info="" customnodeid="" comment="" altitude="121.87" heading="0" copyright="" nodeid="node10" author="" datetime="2024:12:18 07:58:17" longitude="126.677550" description="" latitude="36.649233" tags="2082203VR"/>
    <hotspots wordwrap="1" smoothmovement="0" height="20" width="180">
      <label wordwrap="1" borderalpha="1" textcolor="0x000000" textalpha="1" enabled="1" width="180" background="1" border="1" bordercolor="0x000000" backgroundcolor="0xffffff" height="20" borderradius="1" backgroundalpha="1"/>
      <polystyle handcursor="1" borderalpha="1" backgroundcolor="0x0000ff" mode="0" backgroundalpha="0.25098" bordercolor="0x0000ff"/>
      <hotspot url="{node4}" target="" title="복도3" description="" skinid="ht_node" tilt="-23.4" pan="-141.17" id="Point01"/>
      <hotspot url="{node7}" target="" title="드레스룸" description="" skinid="ht_node" tilt="-24.77" pan="-107.12" id="Point02"/>
      <hotspot url="{node13}" target="" title="거실" description="" skinid="ht_node" tilt="-22.47" pan="-65.18" id="Point03"/>
      <hotspot url="{node9}" target="" title="발코니1" description="" skinid="ht_node" tilt="-26.66" pan="-346.45" id="Point04"/>
    </hotspots>
    <media/>
    <transition type="crossdissolve" delay="none" softedge="0" blendtime="1" enabled="1" zoomafteroutfov="40" zoomspeed="2" zoomin="0" zoomafterinfov="140" zoomfov="40" zoomout="0" blendcolor="0x000000" zoomoutpause="1"/>
    <autorotate speed="0.020" delay="10.00" nodefilter="" enabled="1" returntohorizon="0.000" useanimation="0" horizonfromdefview="0" nodedelay="0.00" startloaded="0" noderandom="1"/>
    <animation syncanimationwithvideo="0" useinautorotation="0" animsequence="Animation01" clipsrandom="0"/>
    <control speedwheel="1" zoomcentercursor="1" sensitivity="8" lockedmouse="0" lockedkeyboardzoom="0" lockedkeyboard="0" invertcontrol="1" dblclickfullscreen="0" simulatemass="1" contextvr="1" contextprojections="0" invertwheel="0" contextfullscreen="1" rubberband="0" hideabout="1" lockedwheel="0"/>
  </panorama>
  <panorama hideabout="1" id="node7">
    <input levelingpitch="0" width="1472" levelbias="0.400" levelingroll="0" leveltileurl="tiles/node7/cf_%c/l_%l/c_%x/tile_%y.jpg" levelbiashidpi="1.000" leveltilesize="510" height="1472" overlap="1">
      <level predecode="0" preload="0" height="1472" width="1472"/>
      <level predecode="0" preload="0" height="736" width="736"/>
      <level predecode="1" preload="1" height="368" width="368"/>
      <preview color="0x808080" strip="1"/>
    </input>
    <view fovmode="2" pannorth="0">
      <start fov="148.415" tilt="-14.4844" pan="60.2615" projection="4"/>
      <flyin fov="170" tilt="-90" pan="0" projection="9"/>
      <min fovpixel="2" tilt="-90" pan="0"/>
      <max scaletofit="1" fovstereographic="330" fov="140" tilt="90" pan="360" fovfisheye="360"/>
    </view>
    <userdata title="드레스룸" source="" info="" customnodeid="" comment="" altitude="121.87" heading="0" copyright="" nodeid="node7" author="" datetime="2024:12:18 07:58:09" longitude="126.677550" description="" latitude="36.649233" tags="2082203VR"/>
    <hotspots wordwrap="1" smoothmovement="0" height="20" width="180">
      <label wordwrap="1" borderalpha="1" textcolor="0x000000" textalpha="1" enabled="1" width="180" background="1" border="1" bordercolor="0x000000" backgroundcolor="0xffffff" height="20" borderradius="1" backgroundalpha="1"/>
      <polystyle handcursor="1" borderalpha="1" backgroundcolor="0x0000ff" mode="0" backgroundalpha="0.25098" bordercolor="0x0000ff"/>
      <hotspot url="{node10}" target="" title="침실1" description="" skinid="ht_node" tilt="-39.94" pan="-184.16" id="Point01"/>
    </hotspots>
    <media/>
    <transition type="crossdissolve" delay="none" softedge="0" blendtime="1" enabled="1" zoomafteroutfov="40" zoomspeed="2" zoomin="0" zoomafterinfov="140" zoomfov="40" zoomout="0" blendcolor="0x000000" zoomoutpause="1"/>
    <autorotate speed="0.020" delay="10.00" nodefilter="" enabled="1" returntohorizon="0.000" useanimation="0" horizonfromdefview="0" nodedelay="0.00" startloaded="0" noderandom="1"/>
    <animation syncanimationwithvideo="0" useinautorotation="0" animsequence="Animation01" clipsrandom="0"/>
    <control speedwheel="1" zoomcentercursor="1" sensitivity="8" lockedmouse="0" lockedkeyboardzoom="0" lockedkeyboard="0" invertcontrol="1" dblclickfullscreen="0" simulatemass="1" contextvr="1" contextprojections="0" invertwheel="0" contextfullscreen="1" rubberband="0" hideabout="1" lockedwheel="0"/>
  </panorama>
  <panorama hideabout="1" id="node4">
    <input levelingpitch="0" width="1472" levelbias="0.400" levelingroll="0" leveltileurl="tiles/node4/cf_%c/l_%l/c_%x/tile_%y.jpg" levelbiashidpi="1.000" leveltilesize="510" height="1472" overlap="1">
      <level predecode="0" preload="0" height="1472" width="1472"/>
      <level predecode="0" preload="0" height="736" width="736"/>
      <level predecode="1" preload="1" height="368" width="368"/>
      <preview color="0x808080" strip="1"/>
    </input>
    <view fovmode="2" pannorth="0">
      <start fov="148.415" tilt="-9.69467" pan="-172.184" projection="4"/>
      <flyin fov="170" tilt="-90" pan="0" projection="9"/>
      <min fovpixel="2" tilt="-90" pan="0"/>
      <max scaletofit="1" fovstereographic="330" fov="140" tilt="90" pan="360" fovfisheye="360"/>
    </view>
    <userdata title="복도3" source="" info="" customnodeid="" comment="" altitude="121.87" heading="0" copyright="" nodeid="node4" author="" datetime="2024:12:18 07:58:01" longitude="126.677550" description="" latitude="36.649233" tags="2082203VR"/>
    <hotspots wordwrap="1" smoothmovement="0" height="20" width="180">
      <label wordwrap="1" borderalpha="1" textcolor="0x000000" textalpha="1" enabled="1" width="180" background="1" border="1" bordercolor="0x000000" backgroundcolor="0xffffff" height="20" borderradius="1" backgroundalpha="1"/>
      <polystyle handcursor="1" borderalpha="1" backgroundcolor="0x0000ff" mode="0" backgroundalpha="0.25098" bordercolor="0x0000ff"/>
      <hotspot url="{node10}" target="" title="침실1" description="" skinid="ht_node" tilt="-22.38" pan="-153.08" id="Point01"/>
      <hotspot url="{node6}" target="" title="욕실2" description="" skinid="ht_node" tilt="-31.69" pan="-124.58" id="Point02"/>
      <hotspot url="{node3}" target="" title="주방" description="" skinid="ht_node" tilt="-31.44" pan="-222.37" id="Point03"/>
      <hotspot url="{node5}" target="" title="실외기실" description="" skinid="ht_node" tilt="-17.35" pan="-60.57" id="Point04"/>
    </hotspots>
    <media/>
    <transition type="crossdissolve" delay="none" softedge="0" blendtime="1" enabled="1" zoomafteroutfov="40" zoomspeed="2" zoomin="0" zoomafterinfov="140" zoomfov="40" zoomout="0" blendcolor="0x000000" zoomoutpause="1"/>
    <autorotate speed="0.020" delay="10.00" nodefilter="" enabled="1" returntohorizon="0.000" useanimation="0" horizonfromdefview="0" nodedelay="0.00" startloaded="0" noderandom="1"/>
    <animation syncanimationwithvideo="0" useinautorotation="0" animsequence="Animation01" clipsrandom="0"/>
    <control speedwheel="1" zoomcentercursor="1" sensitivity="8" lockedmouse="0" lockedkeyboardzoom="0" lockedkeyboard="0" invertcontrol="1" dblclickfullscreen="0" simulatemass="1" contextvr="1" contextprojections="0" invertwheel="0" contextfullscreen="1" rubberband="0" hideabout="1" lockedwheel="0"/>
  </panorama>
  <panorama hideabout="1" id="node6">
    <input levelingpitch="0" width="1472" levelbias="0.400" levelingroll="0" leveltileurl="tiles/node6/cf_%c/l_%l/c_%x/tile_%y.jpg" levelbiashidpi="1.000" leveltilesize="510" height="1472" overlap="1">
      <level predecode="0" preload="0" height="1472" width="1472"/>
      <level predecode="0" preload="0" height="736" width="736"/>
      <level predecode="1" preload="1" height="368" width="368"/>
      <preview color="0x808080" strip="1"/>
    </input>
    <view fovmode="2" pannorth="0">
      <start fov="148.415" tilt="-12.3112" pan="-88.4149" projection="4"/>
      <flyin fov="170" tilt="-90" pan="0" projection="9"/>
      <min fovpixel="2" tilt="-90" pan="0"/>
      <max scaletofit="1" fovstereographic="330" fov="140" tilt="90" pan="360" fovfisheye="360"/>
    </view>
    <userdata title="욕실2" source="" info="" customnodeid="" comment="" altitude="121.87" heading="0" copyright="" nodeid="node6" author="" datetime="2024:12:18 07:58:07" longitude="126.677550" description="" latitude="36.649233" tags="2082203VR"/>
    <hotspots wordwrap="1" smoothmovement="0" height="20" width="180">
      <label wordwrap="1" borderalpha="1" textcolor="0x000000" textalpha="1" enabled="1" width="180" background="1" border="1" bordercolor="0x000000" backgroundcolor="0xffffff" height="20" borderradius="1" backgroundalpha="1"/>
      <polystyle handcursor="1" borderalpha="1" backgroundcolor="0x0000ff" mode="0" backgroundalpha="0.25098" bordercolor="0x0000ff"/>
      <hotspot url="{node4}" target="" title="복도3" description="" skinid="ht_node" tilt="-28.28" pan="-91.26" id="Point01"/>
    </hotspots>
    <media/>
    <transition type="crossdissolve" delay="none" softedge="0" blendtime="1" enabled="1" zoomafteroutfov="40" zoomspeed="2" zoomin="0" zoomafterinfov="140" zoomfov="40" zoomout="0" blendcolor="0x000000" zoomoutpause="1"/>
    <autorotate speed="0.020" delay="10.00" nodefilter="" enabled="1" returntohorizon="0.000" useanimation="0" horizonfromdefview="0" nodedelay="0.00" startloaded="0" noderandom="1"/>
    <animation syncanimationwithvideo="0" useinautorotation="0" animsequence="Animation01" clipsrandom="0"/>
    <control speedwheel="1" zoomcentercursor="1" sensitivity="8" lockedmouse="0" lockedkeyboardzoom="0" lockedkeyboard="0" invertcontrol="1" dblclickfullscreen="0" simulatemass="1" contextvr="1" contextprojections="0" invertwheel="0" contextfullscreen="1" rubberband="0" hideabout="1" lockedwheel="0"/>
  </panorama>
  <panorama hideabout="1" id="node9">
    <input levelingpitch="0" width="1472" levelbias="0.400" levelingroll="0" leveltileurl="tiles/node9/cf_%c/l_%l/c_%x/tile_%y.jpg" levelbiashidpi="1.000" leveltilesize="510" height="1472" overlap="1">
      <level predecode="0" preload="0" height="1472" width="1472"/>
      <level predecode="0" preload="0" height="736" width="736"/>
      <level predecode="1" preload="1" height="368" width="368"/>
      <preview color="0x808080" strip="1"/>
    </input>
    <view fovmode="2" pannorth="0">
      <start fov="148.415" tilt="-9.71758" pan="-33.4633" projection="4"/>
      <flyin fov="170" tilt="-90" pan="0" projection="9"/>
      <min fovpixel="2" tilt="-90" pan="0"/>
      <max scaletofit="1" fovstereographic="330" fov="140" tilt="90" pan="360" fovfisheye="360"/>
    </view>
    <userdata title="발코니1" source="" info="" customnodeid="" comment="" altitude="121.87" heading="0" copyright="" nodeid="node9" author="" datetime="2024:12:18 07:58:15" longitude="126.677550" description="" latitude="36.649233" tags="2082203VR"/>
    <hotspots wordwrap="1" smoothmovement="0" height="20" width="180">
      <label wordwrap="1" borderalpha="1" textcolor="0x000000" textalpha="1" enabled="1" width="180" background="1" border="1" bordercolor="0x000000" backgroundcolor="0xffffff" height="20" borderradius="1" backgroundalpha="1"/>
      <polystyle handcursor="1" borderalpha="1" backgroundcolor="0x0000ff" mode="0" backgroundalpha="0.25098" bordercolor="0x0000ff"/>
      <hotspot url="{node10}" target="" title="침실1" description="" skinid="ht_node" tilt="-38.34" pan="-162.17" id="Point01"/>
    </hotspots>
    <media/>
    <transition type="crossdissolve" delay="none" softedge="0" blendtime="1" enabled="1" zoomafteroutfov="40" zoomspeed="2" zoomin="0" zoomafterinfov="140" zoomfov="40" zoomout="0" blendcolor="0x000000" zoomoutpause="1"/>
    <autorotate speed="0.020" delay="10.00" nodefilter="" enabled="1" returntohorizon="0.000" useanimation="0" horizonfromdefview="0" nodedelay="0.00" startloaded="0" noderandom="1"/>
    <animation syncanimationwithvideo="0" useinautorotation="0" animsequence="Animation01" clipsrandom="0"/>
    <control speedwheel="1" zoomcentercursor="1" sensitivity="8" lockedmouse="0" lockedkeyboardzoom="0" lockedkeyboard="0" invertcontrol="1" dblclickfullscreen="0" simulatemass="1" contextvr="1" contextprojections="0" invertwheel="0" contextfullscreen="1" rubberband="0" hideabout="1" lockedwheel="0"/>
  </panorama>
  <panorama hideabout="1" id="node5">
    <input levelingpitch="0" width="1472" levelbias="0.400" levelingroll="0" leveltileurl="tiles/node5/cf_%c/l_%l/c_%x/tile_%y.jpg" levelbiashidpi="1.000" leveltilesize="510" height="1472" overlap="1">
      <level predecode="0" preload="0" height="1472" width="1472"/>
      <level predecode="0" preload="0" height="736" width="736"/>
      <level predecode="1" preload="1" height="368" width="368"/>
      <preview color="0x808080" strip="1"/>
    </input>
    <view fovmode="2" pannorth="0">
      <start fov="148.415" tilt="-15.6267" pan="-176.1" projection="4"/>
      <flyin fov="170" tilt="-90" pan="0" projection="9"/>
      <min fovpixel="2" tilt="-90" pan="0"/>
      <max scaletofit="1" fovstereographic="330" fov="140" tilt="90" pan="360" fovfisheye="360"/>
    </view>
    <userdata title="실외기실" source="" info="" customnodeid="" comment="" altitude="121.87" heading="0" copyright="" nodeid="node5" author="" datetime="2024:12:18 07:58:04" longitude="126.677550" description="" latitude="36.649233" tags="2082203VR"/>
    <hotspots wordwrap="1" smoothmovement="0" height="20" width="180">
      <label wordwrap="1" borderalpha="1" textcolor="0x000000" textalpha="1" enabled="1" width="180" background="1" border="1" bordercolor="0x000000" backgroundcolor="0xffffff" height="20" borderradius="1" backgroundalpha="1"/>
      <polystyle handcursor="1" borderalpha="1" backgroundcolor="0x0000ff" mode="0" backgroundalpha="0.25098" bordercolor="0x0000ff"/>
      <hotspot url="{node4}" target="" title="복도3" description="" skinid="ht_node" tilt="-17.08" pan="-172.75" id="Point01"/>
    </hotspots>
    <media/>
    <transition type="crossdissolve" delay="none" softedge="0" blendtime="1" enabled="1" zoomafteroutfov="40" zoomspeed="2" zoomin="0" zoomafterinfov="140" zoomfov="40" zoomout="0" blendcolor="0x000000" zoomoutpause="1"/>
    <autorotate speed="0.020" delay="10.00" nodefilter="" enabled="1" returntohorizon="0.000" useanimation="0" horizonfromdefview="0" nodedelay="0.00" startloaded="0" noderandom="1"/>
    <animation syncanimationwithvideo="0" useinautorotation="0" animsequence="Animation01" clipsrandom="0"/>
    <control speedwheel="1" zoomcentercursor="1" sensitivity="8" lockedmouse="0" lockedkeyboardzoom="0" lockedkeyboard="0" invertcontrol="1" dblclickfullscreen="0" simulatemass="1" contextvr="1" contextprojections="0" invertwheel="0" contextfullscreen="1" rubberband="0" hideabout="1" lockedwheel="0"/>
  </panorama>
  <masternode>
    <userdata copyright="" title="힐스테이트 몬테로이 2단지" description="208동 2203호" comment="109A type" tags="" author=""/>
    <animationsequences>
      <sequence title="Animation01"/>
    </animationsequences>
  </masternode>
</tour>
